LICENSE
bhp/__init__.py
bhp/__main__.py
bhp/lib/output.py
bhp-0.0.1.dist-info/entry_points.txt
bhp-0.0.1.dist-info/LICENSE
bhp-0.0.1.dist-info/WHEEL
bhp-0.0.1.dist-info/METADATA
bhp-0.0.1.dist-info/RECORD
