Metadata-Version: 2.1
Name: bhp
Version: 0.0.1
Summary: 
Home-page: https://github.com/puzzlepeaches/bhp
License: BSD 3-Clause License
Author: Nicholas Anastasi
Author-email: nanastasi@sprocketsecurity.com
Requires-Python: >=3.8,<4.0
Classifier: Environment :: Console
Classifier: License :: Other/Proprietary License
Classifier: Programming Language :: Python :: 3
Classifier: Programming Language :: Python :: 3.10
Classifier: Programming Language :: Python :: 3.8
Classifier: Programming Language :: Python :: 3.9
Classifier: Topic :: Security
Requires-Dist: click
Requires-Dist: rich
Project-URL: Repository, https://github.com/puzzlepeaches/bhp
